ovos_ocp_m3u_plugin/__init__.py
ovos_ocp_m3u_plugin/config.py
ovos_ocp_m3u_plugin/version.py
ovos_ocp_m3u_plugin-0.0.2.dist-info/LICENSE
ovos_ocp_m3u_plugin-0.0.2.dist-info/METADATA
ovos_ocp_m3u_plugin-0.0.2.dist-info/WHEEL
ovos_ocp_m3u_plugin-0.0.2.dist-info/entry_points.txt
ovos_ocp_m3u_plugin-0.0.2.dist-info/top_level.txt
ovos_ocp_m3u_plugin-0.0.2.dist-info/zip-safe
ovos_ocp_m3u_plugin-0.0.2.dist-info/RECORD
